{
    "scopeName": "source.mermaid.file",
    "fileTypes": ["mmd"],
    "patterns": [
      {
        "include": "#mermaid-content"
      }
    ],
    "repository": {
      "mermaid-content": {
        "patterns": [
          {
            "begin": "^\\s*---\\s*$",
            "end": "^\\s*---\\s*$",
            "name": "markup.raw.yaml.frontmatter.mermaid",
            "patterns": [
              { "include": "source.yaml" }
            ]
          },
          {
            "match": "^\\s*%%(?!{).*$",
            "name": "comment.line.percentage.mermaid"
          },
          {
            "begin": "^\\s*%%{",
            "end": "}%%\\s*$",
            "name": "comment.block.percentage.mermaid",
            "patterns": [
              {
                "match": "\"(?:[^\"\\\\]|\\\\.)*\"",
                "name": "string.quoted.double.json.mermaid"
              },
              {
                "match": "\\b(?:true|false|null)\\b",
                "name": "constant.language.json.mermaid"
              },
              {
                "match": "\\b\\d+(?:\\.\\d+)?\\b",
                "name": "constant.numeric.json.mermaid"
              }
            ]
          },
          {
            "begin": "^\\s*(flowchart|flowchart-v2|flowchart-elk|graph)\\b",
            "beginCaptures": {
              "1": { "name": "keyword.control.type.mermaid" }
            },
            "end": "(?=^\\s*(flowchart|flowchart-v2|flowchart-elk|graph|sequenceDiagram|classDiagram|classDiagram-v2|stateDiagram|stateDiagram-v2|erDiagram|requirement|requirementDiagram|quadrantChart|mindmap|timeline|journey|gantt|info|pie|zenuml|radar|radar-beta|packet|packet-beta|architecture|architecture-beta|kanban|block|blockDiagram|block-beta|sankeyDiagram|sankey-beta|sankey|xychart|xychart-beta|C4Context|C4Container|C4Component|C4Dynamic|C4Deployment|gitGraph)\\b|\\z)",
            "name": "meta.diagram.mermaid.flowchart",
            "patterns": [
              { "include": "source.mermaid.flowchart" }
            ]
          },
          {
            "begin": "^\\s*(sequenceDiagram)\\b",
            "beginCaptures": {
              "1": { "name": "keyword.control.type.mermaid" }
            },
            "end": "(?=^\\s*(flowchart|flowchart-v2|flowchart-elk|graph|sequenceDiagram|classDiagram|classDiagram-v2|stateDiagram|stateDiagram-v2|erDiagram|requirement|requirementDiagram|quadrantChart|mindmap|timeline|journey|gantt|info|pie|zenuml|radar|radar-beta|packet|packet-beta|architecture|architecture-beta|kanban|block|blockDiagram|block-beta|sankeyDiagram|sankey-beta|sankey|xychart|xychart-beta|C4Context|C4Container|C4Component|C4Dynamic|C4Deployment|gitGraph)\\b|\\z)",
            "name": "meta.diagram.mermaid.sequenceDiagram",
            "patterns": [
              { "include": "source.mermaid.sequenceDiagram" }
            ]
          },
          {
            "begin": "^\\s*(classDiagram|classDiagram-v2)\\b",
            "beginCaptures": {
              "1": { "name": "keyword.control.type.mermaid" }
            },
            "end": "(?=^\\s*(flowchart|flowchart-v2|flowchart-elk|graph|sequenceDiagram|classDiagram|classDiagram-v2|stateDiagram|stateDiagram-v2|erDiagram|requirement|requirementDiagram|quadrantChart|mindmap|timeline|journey|gantt|info|pie|zenuml|radar|radar-beta|packet|packet-beta|architecture|architecture-beta|kanban|block|blockDiagram|block-beta|sankeyDiagram|sankey-beta|sankey|xychart|xychart-beta|C4Context|C4Container|C4Component|C4Dynamic|C4Deployment|gitGraph)\\b|\\z)",
            "name": "meta.diagram.mermaid.classDiagram",
            "patterns": [
              { "include": "source.mermaid.classDiagram" }
            ]
          },
          {
            "begin": "^\\s*(stateDiagram|stateDiagram-v2)\\b",
            "beginCaptures": {
              "1": { "name": "keyword.control.type.mermaid" }
            },
            "end": "(?=^\\s*(flowchart|flowchart-v2|flowchart-elk|graph|sequenceDiagram|classDiagram|classDiagram-v2|stateDiagram|stateDiagram-v2|erDiagram|requirement|requirementDiagram|quadrantChart|mindmap|timeline|journey|gantt|info|pie|zenuml|radar|radar-beta|packet|packet-beta|architecture|architecture-beta|kanban|block|blockDiagram|block-beta|sankeyDiagram|sankey-beta|sankey|xychart|xychart-beta|C4Context|C4Container|C4Component|C4Dynamic|C4Deployment|gitGraph)\\b|\\z)",
            "name": "meta.diagram.mermaid.stateDiagram",
            "patterns": [
              { "include": "source.mermaid.stateDiagram" }
            ]
          },
          {
            "begin": "^\\s*(erDiagram)\\b",
            "beginCaptures": {
              "1": { "name": "keyword.control.type.mermaid" }
            },
            "end": "(?=^\\s*(flowchart|flowchart-v2|flowchart-elk|graph|sequenceDiagram|classDiagram|classDiagram-v2|stateDiagram|stateDiagram-v2|erDiagram|requirement|requirementDiagram|quadrantChart|mindmap|timeline|journey|gantt|info|pie|zenuml|radar|radar-beta|packet|packet-beta|architecture|architecture-beta|kanban|block|blockDiagram|block-beta|sankeyDiagram|sankey-beta|sankey|xychart|xychart-beta|C4Context|C4Container|C4Component|C4Dynamic|C4Deployment|gitGraph)\\b|\\z)",
            "name": "meta.diagram.mermaid.erDiagram",
            "patterns": [
              { "include": "source.mermaid.erDiagram" }
            ]
          },
          {
            "begin": "^\\s*(requirement|requirementDiagram)\\b",
            "beginCaptures": {
              "1": { "name": "keyword.control.type.mermaid" }
            },
            "end": "(?=^\\s*(flowchart|flowchart-v2|flowchart-elk|graph|sequenceDiagram|classDiagram|classDiagram-v2|stateDiagram|stateDiagram-v2|erDiagram|requirement|requirementDiagram|quadrantChart|mindmap|timeline|journey|gantt|info|pie|zenuml|radar|radar-beta|packet|packet-beta|architecture|architecture-beta|kanban|block|blockDiagram|block-beta|sankeyDiagram|sankey-beta|sankey|xychart|xychart-beta|C4Context|C4Container|C4Component|C4Dynamic|C4Deployment|gitGraph)\\b|\\z)",
            "name": "meta.diagram.mermaid.requirementDiagram",
            "patterns": [
              { "include": "source.mermaid.requirementDiagram" }
            ]
          },
          {
            "begin": "^\\s*(quadrantChart)\\b",
            "beginCaptures": {
              "1": { "name": "keyword.control.type.mermaid" }
            },
            "end": "(?=^\\s*(flowchart|flowchart-v2|flowchart-elk|graph|sequenceDiagram|classDiagram|classDiagram-v2|stateDiagram|stateDiagram-v2|erDiagram|requirement|requirementDiagram|quadrantChart|mindmap|timeline|journey|gantt|info|pie|zenuml|radar|radar-beta|packet|packet-beta|architecture|architecture-beta|kanban|block|blockDiagram|block-beta|sankeyDiagram|sankey-beta|sankey|xychart|xychart-beta|C4Context|C4Container|C4Component|C4Dynamic|C4Deployment|gitGraph)\\b|\\z)",
            "name": "meta.diagram.mermaid.quadrantChart",
            "patterns": [
              { "include": "source.mermaid.quadrantChart" }
            ]
          },
          {
            "begin": "^\\s*(mindmap)\\b",
            "beginCaptures": {
              "1": { "name": "keyword.control.type.mermaid" }
            },
            "end": "(?=^\\s*(flowchart|flowchart-v2|flowchart-elk|graph|sequenceDiagram|classDiagram|classDiagram-v2|stateDiagram|stateDiagram-v2|erDiagram|requirement|requirementDiagram|quadrantChart|mindmap|timeline|journey|gantt|info|pie|zenuml|radar|radar-beta|packet|packet-beta|architecture|architecture-beta|kanban|block|blockDiagram|block-beta|sankeyDiagram|sankey-beta|sankey|xychart|xychart-beta|C4Context|C4Container|C4Component|C4Dynamic|C4Deployment|gitGraph)\\b|\\z)",
            "name": "meta.diagram.mermaid.mindmap",
            "patterns": [
              { "include": "source.mermaid.mindmap" }
            ]
          },
          {
            "begin": "^\\s*(timeline)\\b",
            "beginCaptures": {
              "1": { "name": "keyword.control.type.mermaid" }
            },
            "end": "(?=^\\s*(flowchart|flowchart-v2|flowchart-elk|graph|sequenceDiagram|classDiagram|classDiagram-v2|stateDiagram|stateDiagram-v2|erDiagram|requirement|requirementDiagram|quadrantChart|mindmap|timeline|journey|gantt|info|pie|zenuml|radar|radar-beta|packet|packet-beta|architecture|architecture-beta|kanban|block|blockDiagram|block-beta|sankeyDiagram|sankey-beta|sankey|xychart|xychart-beta|C4Context|C4Container|C4Component|C4Dynamic|C4Deployment|gitGraph)\\b|\\z)",
            "name": "meta.diagram.mermaid.timeline",
            "patterns": [
              { "include": "source.mermaid.timeline" }
            ]
          },
          {
            "begin": "^\\s*(journey)\\b",
            "beginCaptures": {
              "1": { "name": "keyword.control.type.mermaid" }
            },
            "end": "(?=^\\s*(flowchart|flowchart-v2|flowchart-elk|graph|sequenceDiagram|classDiagram|classDiagram-v2|stateDiagram|stateDiagram-v2|erDiagram|requirement|requirementDiagram|quadrantChart|mindmap|timeline|journey|gantt|info|pie|zenuml|radar|radar-beta|packet|packet-beta|architecture|architecture-beta|kanban|block|blockDiagram|block-beta|sankeyDiagram|sankey-beta|sankey|xychart|xychart-beta|C4Context|C4Container|C4Component|C4Dynamic|C4Deployment|gitGraph)\\b|\\z)",
            "name": "meta.diagram.mermaid.journey",
            "patterns": [
              { "include": "source.mermaid.journey" }
            ]
          },
          {
            "begin": "^\\s*(gantt|section)\\b",
            "beginCaptures": {
              "1": { "name": "keyword.control.type.mermaid" }
            },
            "end": "(?=^\\s*(flowchart|flowchart-v2|flowchart-elk|graph|sequenceDiagram|classDiagram|classDiagram-v2|stateDiagram|stateDiagram-v2|erDiagram|requirement|requirementDiagram|quadrantChart|mindmap|timeline|journey|gantt|info|pie|zenuml|radar|radar-beta|packet|packet-beta|architecture|architecture-beta|kanban|block|blockDiagram|block-beta|sankeyDiagram|sankey-beta|sankey|xychart|xychart-beta|C4Context|C4Container|C4Component|C4Dynamic|C4Deployment|gitGraph)\\b|\\z)",
            "name": "meta.diagram.mermaid.gantt",
            "patterns": [
              { "include": "source.mermaid.gantt" }
            ]
          },
          {
            "begin": "^\\s*(info)\\b",
            "beginCaptures": {
              "1": { "name": "keyword.control.type.mermaid" }
            },
            "end": "(?=^\\s*(flowchart|flowchart-v2|flowchart-elk|graph|sequenceDiagram|classDiagram|classDiagram-v2|stateDiagram|stateDiagram-v2|erDiagram|requirement|requirementDiagram|quadrantChart|mindmap|timeline|journey|gantt|info|pie|zenuml|radar|radar-beta|packet|packet-beta|architecture|architecture-beta|kanban|block|blockDiagram|block-beta|sankeyDiagram|sankey-beta|sankey|xychart|xychart-beta|C4Context|C4Container|C4Component|C4Dynamic|C4Deployment|gitGraph)\\b|\\z)",
            "name": "meta.diagram.mermaid.info",
            "patterns": [
              { "include": "source.mermaid.info" }
            ]
          },
          {
            "begin": "^\\s*(pie)\\b",
            "beginCaptures": {
              "1": { "name": "keyword.control.type.mermaid" }
            },
            "end": "(?=^\\s*(flowchart|flowchart-v2|flowchart-elk|graph|sequenceDiagram|classDiagram|classDiagram-v2|stateDiagram|stateDiagram-v2|erDiagram|requirement|requirementDiagram|quadrantChart|mindmap|timeline|journey|gantt|info|pie|zenuml|radar|radar-beta|packet|packet-beta|architecture|architecture-beta|kanban|block|blockDiagram|block-beta|sankeyDiagram|sankey-beta|sankey|xychart|xychart-beta|C4Context|C4Container|C4Component|C4Dynamic|C4Deployment|gitGraph)\\b|\\z)",
            "name": "meta.diagram.mermaid.pie",
            "patterns": [
              { "include": "source.mermaid.pie" }
            ]
          },
          {
            "begin": "^\\s*(zenuml)\\b",
            "beginCaptures": {
              "1": { "name": "keyword.control.type.mermaid" }
            },
            "end": "(?=^\\s*(flowchart|flowchart-v2|flowchart-elk|graph|sequenceDiagram|classDiagram|classDiagram-v2|stateDiagram|stateDiagram-v2|erDiagram|requirement|requirementDiagram|quadrantChart|mindmap|timeline|journey|gantt|info|pie|zenuml|radar|radar-beta|packet|packet-beta|architecture|architecture-beta|kanban|block|blockDiagram|block-beta|sankeyDiagram|sankey-beta|sankey|xychart|xychart-beta|C4Context|C4Container|C4Component|C4Dynamic|C4Deployment|gitGraph)\\b|\\z)",
            "name": "meta.diagram.mermaid.zenuml",
            "patterns": [
              { "include": "source.mermaid.zenuml" }
            ]
          },
          {
            "begin": "^\\s*(radar|radar-beta)\\b",
            "beginCaptures": {
              "1": { "name": "keyword.control.type.mermaid" }
            },
            "end": "(?=^\\s*(flowchart|flowchart-v2|flowchart-elk|graph|sequenceDiagram|classDiagram|classDiagram-v2|stateDiagram|stateDiagram-v2|erDiagram|requirement|requirementDiagram|quadrantChart|mindmap|timeline|journey|gantt|info|pie|zenuml|radar|radar-beta|packet|packet-beta|architecture|architecture-beta|kanban|block|blockDiagram|block-beta|sankeyDiagram|sankey-beta|sankey|xychart|xychart-beta|C4Context|C4Container|C4Component|C4Dynamic|C4Deployment|gitGraph)\\b|\\z)",
            "name": "meta.diagram.mermaid.radar",
            "patterns": [
              { "include": "source.mermaid.radar" }
            ]
          },
          {
            "begin": "^\\s*(packet|packet-beta)\\b",
            "beginCaptures": {
              "1": { "name": "keyword.control.type.mermaid" }
            },
            "end": "(?=^\\s*(flowchart|flowchart-v2|flowchart-elk|graph|sequenceDiagram|classDiagram|classDiagram-v2|stateDiagram|stateDiagram-v2|erDiagram|requirement|requirementDiagram|quadrantChart|mindmap|timeline|journey|gantt|info|pie|zenuml|radar|radar-beta|packet|packet-beta|architecture|architecture-beta|kanban|block|blockDiagram|block-beta|sankeyDiagram|sankey-beta|sankey|xychart|xychart-beta|C4Context|C4Container|C4Component|C4Dynamic|C4Deployment|gitGraph)\\b|\\z)",
            "name": "meta.diagram.mermaid.packet",
            "patterns": [
              { "include": "source.mermaid.packet" }
            ]
          },
          {
            "begin": "^\\s*(architecture|architecture-beta)\\b",
            "beginCaptures": {
              "1": { "name": "keyword.control.type.mermaid" }
            },
            "end": "(?=^\\s*(flowchart|flowchart-v2|flowchart-elk|graph|sequenceDiagram|classDiagram|classDiagram-v2|stateDiagram|stateDiagram-v2|erDiagram|requirement|requirementDiagram|quadrantChart|mindmap|timeline|journey|gantt|info|pie|zenuml|radar|radar-beta|packet|packet-beta|architecture|architecture-beta|kanban|block|blockDiagram|block-beta|sankeyDiagram|sankey-beta|sankey|xychart|xychart-beta|C4Context|C4Container|C4Component|C4Dynamic|C4Deployment|gitGraph)\\b|\\z)",
            "name": "meta.diagram.mermaid.architecture",
            "patterns": [
              { "include": "source.mermaid.architecture" }
            ]
          },
          {
            "begin": "^\\s*(kanban)\\b",
            "beginCaptures": {
              "1": { "name": "keyword.control.type.mermaid" }
            },
            "end": "(?=^\\s*(flowchart|flowchart-v2|flowchart-elk|graph|sequenceDiagram|classDiagram|classDiagram-v2|stateDiagram|stateDiagram-v2|erDiagram|requirement|requirementDiagram|quadrantChart|mindmap|timeline|journey|gantt|info|pie|zenuml|radar|radar-beta|packet|packet-beta|architecture|architecture-beta|kanban|block|blockDiagram|block-beta|sankeyDiagram|sankey-beta|sankey|xychart|xychart-beta|C4Context|C4Container|C4Component|C4Dynamic|C4Deployment|gitGraph)\\b|\\z)",
            "name": "meta.diagram.mermaid.kanban",
            "patterns": [
              { "include": "source.mermaid.kanban" }
            ]
          },
          {
            "begin": "^\\s*(block|blockDiagram|block-beta)\\b",
            "beginCaptures": {
              "1": { "name": "keyword.control.type.mermaid" }
            },
            "end": "(?=^\\s*(flowchart|flowchart-v2|flowchart-elk|graph|sequenceDiagram|classDiagram|classDiagram-v2|stateDiagram|stateDiagram-v2|erDiagram|requirement|requirementDiagram|quadrantChart|mindmap|timeline|journey|gantt|info|pie|zenuml|radar|radar-beta|packet|packet-beta|architecture|architecture-beta|kanban|block|blockDiagram|block-beta|sankeyDiagram|sankey-beta|sankey|xychart|xychart-beta|C4Context|C4Container|C4Component|C4Dynamic|C4Deployment|gitGraph)\\b|\\z)",
            "name": "meta.diagram.mermaid.block",
            "patterns": [
              { "include": "source.mermaid.block" }
            ]
          },
          {
            "begin": "^\\s*(sankeyDiagram|sankey-beta|sankey)\\b",
            "beginCaptures": {
              "1": { "name": "keyword.control.type.mermaid" }
            },
            "end": "(?=^\\s*(flowchart|flowchart-v2|flowchart-elk|graph|sequenceDiagram|classDiagram|classDiagram-v2|stateDiagram|stateDiagram-v2|erDiagram|requirement|requirementDiagram|quadrantChart|mindmap|timeline|journey|gantt|info|pie|zenuml|radar|radar-beta|packet|packet-beta|architecture|architecture-beta|kanban|block|blockDiagram|block-beta|sankeyDiagram|sankey-beta|sankey|xychart|xychart-beta|C4Context|C4Container|C4Component|C4Dynamic|C4Deployment|gitGraph)\\b|\\z)",
            "name": "meta.diagram.mermaid.sankeyDiagram",
            "patterns": [
              { "include": "source.mermaid.sankey" }
            ]
          },
          {
            "begin": "^\\s*(xychart|xychart-beta)\\b",
            "beginCaptures": {
              "1": { "name": "keyword.control.type.mermaid" }
            },
            "end": "(?=^\\s*(flowchart|flowchart-v2|flowchart-elk|graph|sequenceDiagram|classDiagram|classDiagram-v2|stateDiagram|stateDiagram-v2|erDiagram|requirement|requirementDiagram|quadrantChart|mindmap|timeline|journey|gantt|info|pie|zenuml|radar|radar-beta|packet|packet-beta|architecture|architecture-beta|kanban|block|blockDiagram|block-beta|sankeyDiagram|sankey-beta|sankey|xychart|xychart-beta|C4Context|C4Container|C4Component|C4Dynamic|C4Deployment|gitGraph)\\b|\\z)",
            "name": "meta.diagram.mermaid.xychart",
            "patterns": [
              { "include": "source.mermaid.xychart" }
            ]
          },
          {
            "begin": "^\\s*(C4Context|C4Container|C4Component|C4Dynamic|C4Deployment)\\b",
            "beginCaptures": {
              "1": { "name": "keyword.control.type.mermaid" }
            },
            "end": "(?=^\\s*(flowchart|flowchart-v2|flowchart-elk|graph|sequenceDiagram|classDiagram|classDiagram-v2|stateDiagram|stateDiagram-v2|erDiagram|requirement|requirementDiagram|quadrantChart|mindmap|timeline|journey|gantt|info|pie|zenuml|radar|radar-beta|packet|packet-beta|architecture|architecture-beta|kanban|block|blockDiagram|block-beta|sankeyDiagram|sankey-beta|sankey|xychart|xychart-beta|C4Context|C4Container|C4Component|C4Dynamic|C4Deployment|gitGraph)\\b|\\z)",
            "name": "meta.diagram.mermaid.c4Diagram",
            "patterns": [
              { "include": "source.mermaid.c4Diagram" }
            ]
          },
          {
            "begin": "^\\s*(gitGraph)\\b",
            "beginCaptures": {
              "1": { "name": "keyword.control.type.mermaid" }
            },
            "end": "(?=^\\s*(flowchart|flowchart-v2|flowchart-elk|graph|sequenceDiagram|classDiagram|classDiagram-v2|stateDiagram|stateDiagram-v2|erDiagram|requirement|requirementDiagram|quadrantChart|mindmap|timeline|journey|gantt|info|pie|zenuml|radar|radar-beta|packet|packet-beta|architecture|architecture-beta|kanban|block|blockDiagram|block-beta|sankeyDiagram|sankey-beta|sankey|xychart|xychart-beta|C4Context|C4Container|C4Component|C4Dynamic|C4Deployment|gitGraph)\\b|\\z)",
            "name": "meta.diagram.mermaid.gitGraph",
            "patterns": [
              { "include": "source.mermaid.gitGraph" }
            ]
          }
        ]
      }
    }
  }